{
  "main": {
    "id": "a3c6ce43543af494",
    "type": "split",
    "children": [
      {
        "id": "a8f7895d1bf378d9",
        "type": "tabs",
        "children": [
          {
            "id": "26a8117e9c0178a5",
            "type": "leaf",
            "state": {
              "type": "graph",
              "state": {},
              "icon": "lucide-git-fork",
              "title": "Граф"
            }
          }
        ]
      }
    ],
    "direction": "vertical"
  },
  "left": {
    "id": "49a370a572fbf7c5",
    "type": "split",
    "children": [
      {
        "id": "602961fdc98a93af",
        "type": "tabs",
        "children": [
          {
            "id": "21dc771547d2f7c9",
            "type": "leaf",
            "state": {
              "type": "file-explorer",
              "state": {
                "sortOrder": "alphabetical"
              },
              "icon": "lucide-folder-closed",
              "title": "Файловый менеджер"
            }
          },
          {
            "id": "871ad1ae45102fd7",
            "type": "leaf",
            "state": {
              "type": "search",
              "state": {
                "query": "",
                "matchingCase": false,
                "explainSearch": false,
                "collapseAll": false,
                "extraContext": false,
                "sortOrder": "alphabetical"
              },
              "icon": "lucide-search",
              "title": "Поиск"
            }
          },
          {
            "id": "642d11b348daec99",
            "type": "leaf",
            "state": {
              "type": "bookmarks",
              "state": {},
              "icon": "lucide-bookmark",
              "title": "Закладки"
            }
          }
        ]
      }
    ],
    "direction": "horizontal",
    "width": 300
  },
  "right": {
    "id": "35f0f8f9640eef54",
    "type": "split",
    "children": [
      {
        "id": "fc0e2ef917f87d1d",
        "type": "tabs",
        "children": [
          {
            "id": "cd223ac392cebaf8",
            "type": "leaf",
            "state": {
              "type": "backlink",
              "state": {
                "collapseAll": false,
                "extraContext": false,
                "sortOrder": "alphabetical",
                "showSearch": false,
                "searchQuery": "",
                "backlinkCollapsed": false,
                "unlinkedCollapsed": true
              },
              "icon": "links-coming-in",
              "title": "Обратные ссылки"
            }
          },
          {
            "id": "8ebd1fd6f1843d6a",
            "type": "leaf",
            "state": {
              "type": "outgoing-link",
              "state": {
                "linksCollapsed": false,
                "unlinkedCollapsed": true
              },
              "icon": "links-going-out",
              "title": "Исходящие ссылки"
            }
          },
          {
            "id": "37831c6c8d699173",
            "type": "leaf",
            "state": {
              "type": "tag",
              "state": {
                "sortOrder": "frequency",
                "useHierarchy": true
              },
              "icon": "lucide-tags",
              "title": "Теги"
            }
          },
          {
            "id": "b640d842bd23b719",
            "type": "leaf",
            "state": {
              "type": "outline",
              "state": {},
              "icon": "lucide-list",
              "title": "Структура"
            }
          }
        ]
      }
    ],
    "direction": "horizontal",
    "width": 300,
    "collapsed": true
  },
  "left-ribbon": {
    "hiddenItems": {
      "switcher:Меню быстрого перехода": false,
      "graph:Граф": false,
      "canvas:Создать новый холст": false,
      "daily-notes:Сегодняшняя заметка": false,
      "templates:Вставить шаблон": false,
      "command-palette:Открыть палитру команд": false
    }
  },
  "active": "26a8117e9c0178a5",
  "lastOpenFiles": [
    "Без названия.canvas"
  ]
}